bigtree_log/__init__.py
bigtree_log/backends.py
bigtree_log/models.py
bigtree_log-0.0.1.dist-info/DESCRIPTION.rst
bigtree_log-0.0.1.dist-info/METADATA
bigtree_log-0.0.1.dist-info/RECORD
bigtree_log-0.0.1.dist-info/WHEEL
bigtree_log-0.0.1.dist-info/metadata.json
bigtree_log-0.0.1.dist-info/top_level.txt
